dekeyrej_kube-1.0.1.dist-info/licenses/LICENSE
kube/__init__.py
kube/kube_secrets.py
dekeyrej_kube-1.0.1.dist-info/METADATA
dekeyrej_kube-1.0.1.dist-info/WHEEL
dekeyrej_kube-1.0.1.dist-info/top_level.txt
dekeyrej_kube-1.0.1.dist-info/RECORD
