Metadata-Version: 2.4
Name: dekeyrej-kube
Version: 1.0.1
Summary: Class and convenience functions for creating, reading, updating, and deleting Kubernetes cluster secrets
Author: J.DeKeyrel
Author-email: "J. DeKeyrel" <noneyabusiness@notemail.com>
License: MIT License
Classifier: License :: OSI Approved :: MIT License
Classifier: Programming Language :: Python
Classifier: Programming Language :: Python :: 3
Requires-Python: >=3.9
License-File: LICENSE
Requires-Dist: kubernetes
Dynamic: author
Dynamic: license-file
